handybox/__init__.py
handybox/datetools.py
handybox/misctools.py
handybox/stringtools.py
handybox-0.4.1.dist-info/licenses/LICENSE
handybox-0.4.1.dist-info/METADATA
handybox-0.4.1.dist-info/WHEEL
handybox-0.4.1.dist-info/top_level.txt
handybox-0.4.1.dist-info/RECORD
