Metadata-Version: 2.4
Name: handybox
Version: 0.4.1
Summary: A lightweight toolbox of handy Python helper functions
Author-email: Gabriel Valentoni Guelfi <gabriel.valguelfi@gmail.com>
License: MIT License 
Keywords: utilities,helpers,toolkit,python
License-File: LICENSE
Dynamic: license-file
